setup.py
formpump/__init__.py
formpump/base.py
formpump/jinjapump.py
formpump/makopump.py
formpump.egg-info/PKG-INFO
formpump.egg-info/SOURCES.txt
formpump.egg-info/dependency_links.txt
formpump.egg-info/top_level.txt
formpump/test/__init__.py
formpump/test/base.py
formpump/test/jinjatests.py
formpump/test/makotests.py