Metadata-Version: 1.0
Name: formpump
Version: 0.1.8
Summary: FormPump is a tool that integrates with popular templating engines, allowing you to cleanly fill in HTML forms
Home-page: https://github.com/mankyd/formpump
Author: Dave Mankoff
Author-email: mankyd@gmail.com
License: http://www.apache.org/licenses/LICENSE-2.0
Platform: UNKNOWN
